{
  "info": {
    "_postman_id": "8e538470-6b0e-44bd-abb5-7790737c8195",
    "name": "electronicStrore",
    "schema": "https://schema.getpostman.com/json/collection/v2.1.0/collection.json"
  },
  "item": [
    {
      "name": "user",
      "item": [
        {
          "name": "createUser",
          "id": "9d13a0b9-6fe3-4927-a5be-822f075c3468",
          "request": {
            "method": "POST",
            "header": [],
            "body": {
              "mode": "raw",
              "raw": "{\n            \"name\": \"harsh\",\n            \"email\": \"harsh@gmail.com\",\n            \"gender\": \"MALE\",\n            \"password\": \"test555555\",\n            \"about\": null,\n            \"imagePath\": \"iuavbf.jpg\"\n        }",
              "options": {
                "raw": {
                  "language": "json"
                }
              }
            },
            "url": {
              "raw": "http://localhost:8080/api/v1/users",
              "protocol": "http",
              "host": [
                "localhost"
              ],
              "port": "8080",
              "path": [
                "api",
                "v1",
                "users"
              ]
            }
          },
          "response": []
        },
        {
          "name": "API Gateway",
          "id": "ca4ebcce-c103-4655-9f67-d27274021625",
          "request": {
            "method": "GET",
            "header": [],
            "url": {
              "raw": ""
            }
          },
          "response": []
        },
        {
          "name": "uploadImage",
          "id": "df5d956b-b7f6-4fba-a884-24a294383c7e",
          "request": {
            "method": "POST",
            "header": [],
            "body": {
              "mode": "formdata",
              "formdata": [
                {
                  "key": "userImage",
                  "type": "file",
                  "uuid": "d6105756-71b0-4d28-9672-946ff07060bc",
                  "src": [
                    "/Users/taalibzama/Downloads/tron_legacy-wallpaper-2560x1440.jpg"
                  ]
                }
              ]
            },
            "url": {
              "raw": "http://localhost:8080/api/v1/users/image/2108edfb-2036-411f-b6c3-ee6315bf2873",
              "protocol": "http",
              "host": [
                "localhost"
              ],
              "port": "8080",
              "path": [
                "api",
                "v1",
                "users",
                "image",
                "2108edfb-2036-411f-b6c3-ee6315bf2873"
              ]
            }
          },
          "response": []
        },
        {
          "name": "getImage",
          "id": "db679296-2e09-45fa-9a34-50d7720348c9",
          "request": {
            "method": "GET",
            "header": [],
            "url": {
              "raw": "http://localhost:8080/api/v1/users/image/2108edfb-2036-411f-b6c3-ee6315bf2873",
              "protocol": "http",
              "host": [
                "localhost"
              ],
              "port": "8080",
              "path": [
                "api",
                "v1",
                "users",
                "image",
                "2108edfb-2036-411f-b6c3-ee6315bf2873"
              ]
            }
          },
          "response": []
        },
        {
          "name": "deleteuserWithImage",
          "id": "ab278777-4c22-4a6f-8545-d8f561f2d3bd",
          "request": {
            "method": "GET",
            "header": [],
            "url": {
              "raw": ""
            }
          },
          "response": []
        },
        {
          "name": "getAll",
          "id": "6f50043c-2c92-480f-8c33-e17d64f7888b",
          "request": {
            "method": "GET",
            "header": [],
            "url": {
              "raw": "http://localhost:8080/api/v1/users?page=0&size=10",
              "protocol": "http",
              "host": [
                "localhost"
              ],
              "port": "8080",
              "path": [
                "api",
                "v1",
                "users"
              ],
              "query": [
                {
                  "key": "page",
                  "value": "0",
                  "uuid": "a8d0e6d8-fb9f-4122-bc2a-df67bb363e47"
                },
                {
                  "key": "size",
                  "value": "10",
                  "uuid": "ae424977-784c-4e73-92e0-ea8e9d1b1321"
                }
              ]
            }
          },
          "response": []
        },
        {
          "name": "fetchWithpagination",
          "id": "8e258c35-ad2d-4a23-a4a0-dc5410f02259",
          "request": {
            "method": "GET",
            "header": [],
            "url": {
              "raw": "http://localhost:8080/api/v1/users?page=0&size=5&sort=name,asc",
              "protocol": "http",
              "host": [
                "localhost"
              ],
              "port": "8080",
              "path": [
                "api",
                "v1",
                "users"
              ],
              "query": [
                {
                  "key": "page",
                  "value": "0"
                },
                {
                  "key": "size",
                  "value": "5"
                },
                {
                  "key": "sort",
                  "value": "name,asc"
                }
              ]
            },
            "description": "Generated from cURL: curl -X GET \"http://localhost:8080/api/v1/users?page=0&size=5&sort=name,asc\""
          },
          "response": []
        },
        {
          "name": "create user",
          "id": "9c964808-e343-42b5-b128-253c79f3adc8",
          "request": {
            "method": "POST",
            "header": [
              {
                "key": "Content-Type",
                "value": "application/json"
              }
            ],
            "body": {
              "mode": "raw",
              "raw": "{\n    \"name\": \"John Doe\",\n    \"email\": \"john@example.com\",\n    \"password\": \"pass123\",\n    \"gender\": \"MALE\",\n    \"about\": \"Software Developer\",\n    \"imagePath\": \"/images/john.jpg\"\n  }",
              "options": {
                "raw": {
                  "language": "json"
                }
              }
            },
            "url": {
              "raw": "http://localhost:8080/api/v1/users",
              "protocol": "http",
              "host": [
                "localhost"
              ],
              "port": "8080",
              "path": [
                "api",
                "v1",
                "users"
              ]
            },
            "description": "Generated from cURL: curl -X POST http://localhost:8080/api/v1/users \\\n  -H \"Content-Type: application/json\" \\\n  -d '{\n    \"name\": \"John Doe\",\n    \"email\": \"john@example.com\",\n    \"password\": \"pass123\",\n    \"gender\": \"MALE\",\n    \"about\": \"Software Developer\",\n    \"imagePath\": \"/images/john.jpg\"\n  }'\n"
          },
          "response": []
        },
        {
          "name": "getbyID",
          "id": "819767e5-5992-4ff5-8029-28231a7839b7",
          "request": {
            "method": "GET",
            "header": [],
            "url": {
              "raw": ""
            }
          },
          "response": []
        },
        {
          "name": "getuserbyID",
          "id": "93a1e9d7-00eb-4b84-a086-156220984195",
          "request": {
            "method": "GET",
            "header": [],
            "url": {
              "raw": "http://localhost:8080/api/v1/users/123",
              "protocol": "http",
              "host": [
                "localhost"
              ],
              "port": "8080",
              "path": [
                "api",
                "v1",
                "users",
                "123"
              ]
            },
            "description": "Generated from cURL: curl -X GET http://localhost:8080/api/v1/users/123\n"
          },
          "response": []
        },
        {
          "name": "findAllWithSortingAndPagination",
          "id": "bc87a2b6-68a6-43dc-828a-e4c5a75745ea",
          "request": {
            "method": "GET",
            "header": [],
            "url": {
              "raw": "http://localhost:8080/api/v1/users?page=5&size=5&sort=name,asc",
              "protocol": "http",
              "host": [
                "localhost"
              ],
              "port": "8080",
              "path": [
                "api",
                "v1",
                "users"
              ],
              "query": [
                {
                  "key": "page",
                  "value": "5",
                  "uuid": "1d547758-1460-481c-b6f4-e13ab3784086"
                },
                {
                  "key": "size",
                  "value": "5",
                  "uuid": "25c4898c-5fc3-4f93-9309-ab036a9ffa05"
                },
                {
                  "key": "sort",
                  "value": "name,asc",
                  "uuid": "1c7686c0-502d-42c4-a6cd-214428058510"
                }
              ]
            }
          },
          "response": []
        },
        {
          "name": "setRoleToUser",
          "id": "359c97ba-c277-492c-844a-718a16c8fe1c",
          "request": {
            "auth": {
              "type": "noauth"
            },
            "method": "PUT",
            "header": [],
            "url": {
              "raw": "http://localhost:8080/api/v1/users/role?email=john.doe@example.com&roleName=ROLE__NORMAL",
              "protocol": "http",
              "host": [
                "localhost"
              ],
              "port": "8080",
              "path": [
                "api",
                "v1",
                "users",
                "role"
              ],
              "query": [
                {
                  "key": "email",
                  "value": "john.doe@example.com",
                  "uuid": "c788ec48-f7af-449d-8d57-42ff8117a095"
                },
                {
                  "key": "roleName",
                  "value": "ROLE__NORMAL",
                  "uuid": "55580a9d-ac5f-450f-913a-fb482e29b243"
                }
              ]
            }
          },
          "response": []
        }
      ],
      "id": "47bde6f0-b801-4496-99da-12c49f060547"
    },
    {
      "name": "categories",
      "item": [
        {
          "name": "create",
          "id": "45089868-28a1-4ec8-af64-57c45f0d7282",
          "request": {
            "method": "POST",
            "header": [],
            "body": {
              "mode": "raw",
              "raw": "{\n    \"title\" : \"Mobile Phones\",\n    \"description\": \"this cateogor is for mobile phones\",\n    \"coverImage\": \"abc.png\"\n}",
              "options": {
                "raw": {
                  "language": "json"
                }
              }
            },
            "url": {
              "raw": "http://localhost:8080/categories/create",
              "protocol": "http",
              "host": [
                "localhost"
              ],
              "port": "8080",
              "path": [
                "categories",
                "create"
              ]
            }
          },
          "response": []
        },
        {
          "name": "getAll",
          "id": "e825fa41-58f9-4f7b-bf97-99488429cc60",
          "request": {
            "auth": {
              "type": "bearer",
              "bearer": [
                {
                  "key": "token",
                  "value": "eyJhbGciOiJIUzUxMiJ9.eyJzdWIiOiJoYXJzaEBnbWFpbC5jb20iLCJpYXQiOjE3NzAyMTcwOTUsImV4cCI6MTc3MDIzNTA5NX0.X28u9IYmTZcskQrqHE_2XcIQjcsQwMIN5kqEp3ML8LKtM3TFnQys8dFw_oAwM6TQyASzSxG7hKphj5Z7zU-F-g",
                  "type": "string"
                }
              ]
            },
            "method": "GET",
            "header": [],
            "body": {
              "mode": "raw",
              "raw": "{\n    \"title\" : \"Mobile Phones\",\n    \"description\": \"this cateogor is for mobile phones\",\n    \"coverImage\": \"abc.png\"\n}"
            },
            "url": {
              "raw": "http://localhost:8080/categories/getAll",
              "protocol": "http",
              "host": [
                "localhost"
              ],
              "port": "8080",
              "path": [
                "categories",
                "getAll"
              ]
            }
          },
          "response": []
        },
        {
          "name": "getSingle",
          "id": "20eba638-46e8-4eeb-9df4-919db1613e59",
          "request": {
            "method": "GET",
            "header": [],
            "url": {
              "raw": "http://localhost:8080/categories/getSingle/c3def634-0446-47ee-a52d-1d9452e28f2f",
              "protocol": "http",
              "host": [
                "localhost"
              ],
              "port": "8080",
              "path": [
                "categories",
                "getSingle",
                "c3def634-0446-47ee-a52d-1d9452e28f2f"
              ]
            }
          },
          "response": []
        },
        {
          "name": "update",
          "id": "36d8a6dd-4e90-43a9-9155-2523ae8f84d9",
          "request": {
            "method": "PUT",
            "header": [],
            "body": {
              "mode": "raw",
              "raw": "{\n    \"title\": \"Best Sellers of Today\",\n    \"description\": \"this cateogory is for bestselling products on today\",\n    \"coverImage\": \"xyz1.png\"\n}",
              "options": {
                "raw": {
                  "language": "json"
                }
              }
            },
            "url": {
              "raw": "http://localhost:8080/categories/update/c3def634-0446-47ee-a52d-1d9452e28f2f",
              "protocol": "http",
              "host": [
                "localhost"
              ],
              "port": "8080",
              "path": [
                "categories",
                "update",
                "c3def634-0446-47ee-a52d-1d9452e28f2f"
              ]
            }
          },
          "response": []
        },
        {
          "name": "search",
          "id": "cba0390f-c3e8-4e20-ab12-7a033ed915f8",
          "request": {
            "method": "GET",
            "header": [],
            "body": {
              "mode": "raw",
              "raw": "{\n    \"title\" : \"Mobile Phones\",\n    \"description\": \"this cateogor is for mobile phones\",\n    \"coverImage\": \"abc.png\"\n}"
            },
            "url": {
              "raw": "http://localhost:8080/categories/search/trending",
              "protocol": "http",
              "host": [
                "localhost"
              ],
              "port": "8080",
              "path": [
                "categories",
                "search",
                "trending"
              ]
            }
          },
          "response": []
        },
        {
          "name": "delete",
          "id": "89588f62-29c9-4075-98b2-2419ad7196ff",
          "request": {
            "method": "DELETE",
            "header": [],
            "url": {
              "raw": "http://localhost:8080/categories/delete/0e175d7e-9940-4e58-a829-855f9e0b5ad8",
              "protocol": "http",
              "host": [
                "localhost"
              ],
              "port": "8080",
              "path": [
                "categories",
                "delete",
                "0e175d7e-9940-4e58-a829-855f9e0b5ad8"
              ]
            }
          },
          "response": []
        },
        {
          "name": "getImageofcategory",
          "id": "e07bbc1c-535f-4d00-99ce-ff8cfcb08911",
          "request": {
            "method": "GET",
            "header": [],
            "url": {
              "raw": ""
            }
          },
          "response": []
        },
        {
          "name": "uploadImage",
          "id": "0d7907c2-76cb-4ddd-af8d-b57b164f750f",
          "request": {
            "method": "POST",
            "header": [],
            "body": {
              "mode": "formdata",
              "formdata": [
                {
                  "key": "categoryImage",
                  "type": "file",
                  "uuid": "d6105756-71b0-4d28-9672-946ff07060bc",
                  "src": [
                    "/Users/taalibzama/Downloads/tron-wallpaper-2560x1440.jpg"
                  ]
                }
              ]
            },
            "url": {
              "raw": "http://localhost:8080/categories/image/0e175d7e-9940-4e58-a829-855f9e0b5ad8",
              "protocol": "http",
              "host": [
                "localhost"
              ],
              "port": "8080",
              "path": [
                "categories",
                "image",
                "0e175d7e-9940-4e58-a829-855f9e0b5ad8"
              ]
            }
          },
          "response": []
        },
        {
          "name": "updateProductCategory",
          "id": "ce44f092-4161-4c14-af3a-7858233e0000",
          "request": {
            "method": "PUT",
            "header": [],
            "url": {
              "raw": "http://localhost:8080/categories/719211b1-528f-4f2b-80e9-e17066f5871c/products/733d17ca-af54-4453-b8dc-0db0f408de14",
              "protocol": "http",
              "host": [
                "localhost"
              ],
              "port": "8080",
              "path": [
                "categories",
                "719211b1-528f-4f2b-80e9-e17066f5871c",
                "products",
                "733d17ca-af54-4453-b8dc-0db0f408de14"
              ]
            },
            "description": "Generated from cURL: curl -X PUT http://localhost:8080/categories/cat123/products/prod456\n"
          },
          "response": []
        }
      ],
      "id": "517ccd05-38d0-424c-acaf-017798f4e2e2"
    },
    {
      "name": "Product",
      "item": [
        {
          "name": "updatProduct",
          "id": "0c996d36-d795-46bf-a220-b425d0cdfbbf",
          "request": {
            "method": "PUT",
            "header": [
              {
                "key": "Content-Type",
                "value": "application/json"
              },
              {
                "key": "Accept",
                "value": "application/json"
              }
            ],
            "body": {
              "mode": "raw",
              "raw": "{\n    \"title\": \"Updated Title\",\n    \"price\": 179.99,\n    \"isLive\": false\n  }",
              "options": {
                "raw": {
                  "language": "json"
                }
              }
            },
            "url": {
              "raw": "http://localhost:8080/products/40925154-131b-4de7-bad8-aa629c0d1a5d",
              "protocol": "http",
              "host": [
                "localhost"
              ],
              "port": "8080",
              "path": [
                "products",
                "40925154-131b-4de7-bad8-aa629c0d1a5d"
              ]
            },
            "description": "Generated from cURL: curl -i -X PUT http://localhost:8080/products/{productId} \\\n  -H \"Content-Type: application/json\" \\\n  -H \"Accept: application/json\" \\\n  -d '{\n    \"title\": \"Updated Title\",\n    \"price\": 179.99,\n    \"isLive\": false\n  }'"
          },
          "response": []
        },
        {
          "name": "deleteProduct",
          "id": "31a5b82a-5d02-482b-a783-23952f4a067d",
          "request": {
            "method": "DELETE",
            "header": [
              {
                "key": "Accept",
                "value": "application/json"
              }
            ],
            "url": {
              "raw": "http://localhost:8080/products/e55c07ee-4c40-464b-b961-f9063c2a6c94",
              "protocol": "http",
              "host": [
                "localhost"
              ],
              "port": "8080",
              "path": [
                "products",
                "e55c07ee-4c40-464b-b961-f9063c2a6c94"
              ]
            },
            "description": "Generated from cURL: curl -i -X DELETE http://localhost:8080/products/{productId} \\\n  -H \"Accept: application/json\"\n"
          },
          "response": []
        },
        {
          "name": "liveProductWithPaginationAndSorting",
          "id": "23ae82c8-dad2-485a-9e31-a014e4c9dd6e",
          "request": {
            "method": "GET",
            "header": [
              {
                "key": "Accept",
                "value": "application/json"
              }
            ],
            "url": {
              "raw": "http://localhost:8080/products/live?page=0&size=10&sort=addedDate,desc",
              "protocol": "http",
              "host": [
                "localhost"
              ],
              "port": "8080",
              "path": [
                "products",
                "live"
              ],
              "query": [
                {
                  "key": "page",
                  "value": "0"
                },
                {
                  "key": "size",
                  "value": "10"
                },
                {
                  "key": "sort",
                  "value": "addedDate,desc"
                }
              ]
            },
            "description": "Generated from cURL: curl -i -X GET \"http://localhost:8080/products/live?page=0&size=10&sort=addedDate,desc\" \\\n  -H \"Accept: application/json\""
          },
          "response": []
        },
        {
          "name": "searchByTitle",
          "id": "2bf4cdfe-d931-4043-b059-2a105b897f44",
          "request": {
            "method": "GET",
            "header": [
              {
                "key": "Accept",
                "value": "application/json"
              }
            ],
            "url": {
              "raw": "http://localhost:8080/products/search?subTitle=phone&page=0&size=10&sort=addedDate,desc",
              "protocol": "http",
              "host": [
                "localhost"
              ],
              "port": "8080",
              "path": [
                "products",
                "search"
              ],
              "query": [
                {
                  "key": "subTitle",
                  "value": "phone",
                  "uuid": "5b5c4432-00cf-42ad-bb85-8b3f687b82cc"
                },
                {
                  "key": "page",
                  "value": "0",
                  "uuid": "44501d4b-60ca-4af5-965d-5c0edf4b97d5"
                },
                {
                  "key": "size",
                  "value": "10",
                  "uuid": "c8726d14-a08b-4bac-a47e-da107c26d50f"
                },
                {
                  "key": "sort",
                  "value": "addedDate,desc",
                  "uuid": "778fa0b7-d0aa-4526-abd0-53f3ea599820"
                }
              ]
            },
            "description": "Generated from cURL: curl -i -X GET \"http://localhost:8080/products/search?subTitle=phone&page=0&size=10&sort=addedDate,desc\" \\\n  -H \"Accept: application/json\"\n"
          },
          "response": []
        },
        {
          "name": "uploadProductImage",
          "id": "2161ad39-d870-4066-b568-655d646837f9",
          "request": {
            "method": "POST",
            "header": [
              {
                "key": "Accept",
                "value": "application/json"
              }
            ],
            "body": {
              "mode": "formdata",
              "formdata": [
                {
                  "type": "file",
                  "key": "productImage",
                  "src": [
                    "/Users/taalibzama/Downloads/mobile-phone-icon-vector-2382356.jpg"
                  ]
                }
              ]
            },
            "url": {
              "raw": "http://localhost:8080/products/image/40925154-131b-4de7-bad8-aa629c0d1a5d",
              "protocol": "http",
              "host": [
                "localhost"
              ],
              "port": "8080",
              "path": [
                "products",
                "image",
                "40925154-131b-4de7-bad8-aa629c0d1a5d"
              ]
            },
            "description": "Generated from cURL: curl -v -X POST \"http://localhost:8080/products/image/{productId}\" \\\n  -H \"Accept: application/json\" \\\n  -F \"productImage=@/path/to/local/image.jpg\""
          },
          "response": []
        },
        {
          "name": "serve Prodct image",
          "id": "fb9ca62b-020e-47d7-95ee-ebb66bc2bbf4",
          "request": {
            "method": "GET",
            "header": [
              {
                "key": "Accept",
                "value": "image/jpeg"
              }
            ],
            "url": {
              "raw": "http://localhost:8080/products/image/40925154-131b-4de7-bad8-aa629c0d1a5d",
              "protocol": "http",
              "host": [
                "localhost"
              ],
              "port": "8080",
              "path": [
                "products",
                "image",
                "40925154-131b-4de7-bad8-aa629c0d1a5d"
              ]
            },
            "description": "Generated from cURL: curl -v \"http://localhost:8080/products/image/{productId}\" \\\n  -H \"Accept: image/jpeg\" \\\n  -o out.jpg"
          },
          "response": []
        },
        {
          "name": "createProductWithCategory",
          "id": "13bb69c8-9c7b-4553-8a17-aa173395e6c8",
          "request": {
            "method": "POST",
            "header": [
              {
                "key": "Content-Type",
                "value": "application/json"
              }
            ],
            "body": {
              "mode": "raw",
              "raw": "{\n    \"title\": \"Wireless Mouse\",\n    \"description\": \"Ergonomic wireless mouse\",\n    \"price\": 29.99,\n    \"quantity\": 100,\n    \"addedDate\": \"2025-12-24T12:00:00Z\",\n    \"coverImage\": \"mouse.jpg\",\n    \"is_instock\" : true,\n    \"live\": true\n  }",
              "options": {
                "raw": {
                  "language": "json"
                }
              }
            },
            "url": {
              "raw": "http://localhost:8080/categories/05dce501-7ab1-4e55-b615-36e47791f065/products",
              "protocol": "http",
              "host": [
                "localhost"
              ],
              "port": "8080",
              "path": [
                "categories",
                "05dce501-7ab1-4e55-b615-36e47791f065",
                "products"
              ]
            },
            "description": "Generated from cURL: curl -X POST \"http://localhost:8080/categories/cat123/products\" \\\n  -H \"Content-Type: application/json\" \\\n  -d '{\n    \"id\": \"prod123\",\n    \"title\": \"Wireless Mouse\",\n    \"description\": \"Ergonomic wireless mouse\",\n    \"price\": 29.99,\n    \"quantity\": 100,\n    \"addedDate\": \"2025-12-24T12:00:00Z\",\n    \"coverImage\": \"mouse.jpg\",\n    \"live\": true\n  }'\n"
          },
          "response": []
        },
        {
          "name": "createProduct",
          "id": "58b5425e-3f3a-4544-b940-d1741b3a3928",
          "request": {
            "auth": {
              "type": "basic",
              "basic": [
                {
                  "key": "password",
                  "value": "test555555",
                  "type": "string"
                },
                {
                  "key": "username",
                  "value": "harsh@gmail.com",
                  "type": "string"
                }
              ]
            },
            "method": "POST",
            "header": [
              {
                "key": "Content-Type",
                "value": "application/json"
              },
              {
                "key": "Accept",
                "value": "application/json"
              }
            ],
            "body": {
              "mode": "raw",
              "raw": "{\n    \"title\": \"iphone 16\",\n    \"description\": \"Phones\",\n    \"price\": 449.99,\n    \"discountedPrice\": 299.99,\n    \"quantity\": 100,\n    \"isLive\": true,\n    \"addedDate\": \"2025-12-28T12:34:56\",\n    \"isInstock\": true,\n    \"productImage\": null,\n    \"category\": null\n  }",
              "options": {
                "raw": {
                  "language": "json"
                }
              }
            },
            "url": {
              "raw": "http://localhost:8080/products",
              "protocol": "http",
              "host": [
                "localhost"
              ],
              "port": "8080",
              "path": [
                "products"
              ]
            },
            "description": "Generated from cURL: curl -X POST http://localhost:8080/products \\\n  -H \"Content-Type: application/json\" \\\n  -H \"Accept: application/json\" \\\n  -d '{\n    \"productId\": \"prod-123\",\n    \"title\": \"Wireless Mouse\",\n    \"description\": \"Ergonomic wireless mouse\",\n    \"price\": 29.99,\n    \"discountedPrice\": 24.99,\n    \"quantity\": 100,\n    \"isLive\": true,\n    \"addedDate\": \"2025-12-28T12:34:56\",\n    \"isInstock\": true,\n    \"productImage\": null,\n    \"category\": null\n  }'"
          },
          "response": []
        },
        {
          "name": "getAllProductOFOneCategory",
          "id": "b24aa839-43d1-424c-91e8-2e524e686a78",
          "request": {
            "method": "GET",
            "header": [],
            "url": {
              "raw": "http://localhost:8080/categories/05dce501-7ab1-4e55-b615-36e47791f065/products?page=0&size=10&sort=price,desc&sort=title,asc",
              "protocol": "http",
              "host": [
                "localhost"
              ],
              "port": "8080",
              "path": [
                "categories",
                "05dce501-7ab1-4e55-b615-36e47791f065",
                "products"
              ],
              "query": [
                {
                  "key": "page",
                  "value": "0",
                  "uuid": "d88c9710-eff3-4719-a96d-e6f26045fbf5"
                },
                {
                  "key": "size",
                  "value": "10",
                  "uuid": "a1c652ab-3370-4cd6-a6a7-dd645dc072eb"
                },
                {
                  "key": "sort",
                  "value": "price,desc",
                  "uuid": "fc38911a-8e21-410e-afa1-ea600eedff4a"
                },
                {
                  "key": "sort",
                  "value": "title,asc",
                  "uuid": "648e13b3-28ac-494f-86c9-0dec40491f76"
                }
              ]
            },
            "description": "Generated from cURL: curl -X GET \"http://localhost:8080/categories/CATEGORY_ID/products?page=0&size=10&sort=price,desc&sort=title,asc\"\n"
          },
          "response": []
        }
      ],
      "id": "2da47a16-4fbb-4ec1-b049-1b51ee632586"
    },
    {
      "name": "cart",
      "item": [
        {
          "name": "addItemsToCart",
          "id": "069995d4-b0ba-4df3-ad29-80143cb36fe6",
          "request": {
            "method": "POST",
            "header": [
              {
                "key": "Content-Type",
                "value": "application/json"
              }
            ],
            "body": {
              "mode": "raw",
              "raw": "{\n    \"productId\": \"aab09992-14a1-4491-a8c8-4818ba2e46c8\",\n    \"quantity\": 1\n  }",
              "options": {
                "raw": {
                  "language": "json"
                }
              }
            },
            "url": {
              "raw": "http://localhost:8080/api/v1/carts/2108edfb-2036-411f-b6c3-ee6315bf2873/items",
              "protocol": "http",
              "host": [
                "localhost"
              ],
              "port": "8080",
              "path": [
                "api",
                "v1",
                "carts",
                "2108edfb-2036-411f-b6c3-ee6315bf2873",
                "items"
              ]
            },
            "description": "Generated from cURL: curl -X POST http://localhost:8080/api/v1/carts/user123/items \\\n  -H \"Content-Type: application/json\" \\\n  -d '{\n    \"productId\": \"prod456\",\n    \"quantity\": 2\n  }'\n"
          },
          "response": []
        },
        {
          "name": "getUserCartByUserID",
          "id": "0a903441-3cc1-43cd-9cc2-53f427a5b06b",
          "request": {
            "method": "GET",
            "header": [],
            "url": {
              "raw": "http://localhost:8080/api/v1/carts/b6dae65a-cca0-4b07-b35b-9b5cb913f541",
              "protocol": "http",
              "host": [
                "localhost"
              ],
              "port": "8080",
              "path": [
                "api",
                "v1",
                "carts",
                "b6dae65a-cca0-4b07-b35b-9b5cb913f541"
              ]
            },
            "description": "Generated from cURL: curl -X GET http://localhost:8080/api/v1/carts/user123\n"
          },
          "response": []
        },
        {
          "name": "removeItemFromcart",
          "id": "e0618cfd-4409-4c20-8b1b-12e794eb1729",
          "request": {
            "method": "DELETE",
            "header": [],
            "url": {
              "raw": "http://localhost:8080/api/v1/carts/fffd69a3-ac2f-47f0-b97c-af485966c20b/items/2",
              "protocol": "http",
              "host": [
                "localhost"
              ],
              "port": "8080",
              "path": [
                "api",
                "v1",
                "carts",
                "fffd69a3-ac2f-47f0-b97c-af485966c20b",
                "items",
                "2"
              ]
            },
            "description": "Generated from cURL: curl -X DELETE http://localhost:8080/api/v1/carts/user123/items/1\n"
          },
          "response": []
        },
        {
          "name": "clearCart",
          "id": "69ce7f2d-34b1-49f2-9fad-c8cbd004eada",
          "request": {
            "method": "DELETE",
            "header": [],
            "url": {
              "raw": "http://localhost:8080/api/v1/carts/fffd69a3-ac2f-47f0-b97c-af485966c20b",
              "protocol": "http",
              "host": [
                "localhost"
              ],
              "port": "8080",
              "path": [
                "api",
                "v1",
                "carts",
                "fffd69a3-ac2f-47f0-b97c-af485966c20b"
              ]
            },
            "description": "Generated from cURL: curl -X DELETE http://localhost:8080/api/v1/carts/user123\n"
          },
          "response": []
        },
        {
          "name": "New Request",
          "id": "67708d03-df09-4087-9a34-21f240123a83",
          "request": {
            "method": "GET",
            "header": [],
            "url": {
              "raw": ""
            }
          },
          "response": []
        }
      ],
      "id": "2c7fae2b-c4be-4875-a94e-5fe4ff46ddec"
    },
    {
      "name": "order",
      "item": [
        {
          "name": "crateOrder",
          "id": "4c04344b-c8d6-4bd1-84e4-6577831371ed",
          "request": {
            "method": "POST",
            "header": [],
            "body": {
              "mode": "raw",
              "raw": "{\n    \"cartId\" : \"9044422f-971a-4160-970c-8c90ef5f271b\",\n    \"userId\" : \"b6dae65a-cca0-4b07-b35b-9b5cb913f541\",\n    \"billingAddress\" : \"H,No 15,Ranchi,Jharkhand,834004, India\",\n    \"billingPhone\" : \"7879679301\",\n    \"billingName\" : \"Taalib\"\n\n}",
              "options": {
                "raw": {
                  "language": "json"
                }
              }
            },
            "url": {
              "raw": "http://localhost:8080/orders",
              "protocol": "http",
              "host": [
                "localhost"
              ],
              "port": "8080",
              "path": [
                "orders"
              ]
            }
          },
          "response": []
        },
        {
          "name": "getOrdersOfUser",
          "id": "85b34a56-2f51-41ab-a242-c45a0e7a791a",
          "request": {
            "method": "GET",
            "header": [],
            "url": {
              "raw": "http://localhost:8080/orders/users/b6dae65a-cca0-4b07-b35b-9b5cb913f541",
              "protocol": "http",
              "host": [
                "localhost"
              ],
              "port": "8080",
              "path": [
                "orders",
                "users",
                "b6dae65a-cca0-4b07-b35b-9b5cb913f541"
              ]
            }
          },
          "response": []
        },
        {
          "name": "getAllORdersInApplication",
          "id": "e9cb4a6a-0f10-452f-bba9-af606069a140",
          "request": {
            "method": "GET",
            "header": [],
            "url": {
              "raw": "http://localhost:8080/orders",
              "protocol": "http",
              "host": [
                "localhost"
              ],
              "port": "8080",
              "path": [
                "orders"
              ]
            }
          },
          "response": []
        },
        {
          "name": "removeOrder",
          "id": "a895f728-33dc-493f-8087-d747a713f0fb",
          "request": {
            "method": "DELETE",
            "header": [],
            "url": {
              "raw": "http://localhost:8080/orders/f2e974b6-b303-4cfb-b7cc-da77627a0786",
              "protocol": "http",
              "host": [
                "localhost"
              ],
              "port": "8080",
              "path": [
                "orders",
                "f2e974b6-b303-4cfb-b7cc-da77627a0786"
              ]
            }
          },
          "response": []
        }
      ],
      "id": "b4a5b51f-da64-4a3b-906b-b7ea9a742d08"
    },
    {
      "name": "auth",
      "item": [
        {
          "name": "http://localhost:8080/auth/generate-token",
          "id": "d73777f0-1a91-4a04-a24d-c98ece6ba177",
          "request": {
            "method": "POST",
            "header": [],
            "body": {
              "mode": "raw",
              "raw": "{\n    \"email\" : \"harsh@gmail.com\",\n    \"password\" : \"test555555\"\n}",
              "options": {
                "raw": {
                  "language": "json"
                }
              }
            },
            "url": {
              "raw": "http://localhost:8080/auth/generate-token",
              "protocol": "http",
              "host": [
                "localhost"
              ],
              "port": "8080",
              "path": [
                "auth",
                "generate-token"
              ]
            }
          },
          "response": []
        }
      ],
      "id": "17801d1c-911a-41c0-a13e-cd8fe9660913"
    }
  ],
  "variable": [
    {
      "id": "aafcc625-5d45-48b0-b940-f7bbde1d15a5",
      "key": "baseURL",
      "value": "",
      "type": "default"
    }
  ]
}